pdit/__init__.py
pdit/_demo.py
pdit/cli.py
pdit/exporter.py
pdit/file_watcher.py
pdit/ipython_executor.py
pdit/server.py
pdit/_static/export.html
pdit/_static/index.html
pdit/_static/assets/index-DbESVfT-.js
pdit/_static/assets/index-rS96z8hq.css
pdit-0.6.0.dist-info/licenses/LICENSE
pdit-0.6.0.dist-info/METADATA
pdit-0.6.0.dist-info/WHEEL
pdit-0.6.0.dist-info/entry_points.txt
pdit-0.6.0.dist-info/top_level.txt
pdit-0.6.0.dist-info/RECORD
