Metadata-Version: 2.4
Name: pdit
Version: 0.6.0
Summary: Interactive Python code editor with inline execution results
Author: Harry Vangberg
License: MIT
Project-URL: Homepage, https://github.com/vangberg/pdit
Project-URL: Repository, https://github.com/vangberg/pdit
Project-URL: Issues, https://github.com/vangberg/pdit/issues
Classifier: Development Status :: 3 - Alpha
Classifier: Intended Audience :: Developers
Classifier: Programming Language :: Python :: 3
Classifier: Programming Language :: Python :: 3.8
Classifier: Programming Language :: Python :: 3.9
Classifier: Programming Language :: Python :: 3.10
Classifier: Programming Language :: Python :: 3.11
Classifier: Programming Language :: Python :: 3.12
Requires-Python: <3.14,>=3.9
License-File: LICENSE
Requires-Dist: fastapi>=0.104.0
Requires-Dist: uvicorn[standard]>=0.24.0
Requires-Dist: typer>=0.9.0
Requires-Dist: aiofiles>=23.0.0
Requires-Dist: watchfiles>=0.20.0
Requires-Dist: jupyter_client>=8.0.0
Requires-Dist: ipykernel>=6.29.0
Requires-Dist: itables>=2.6.1
Requires-Dist: ipython>=8.18.1
Provides-Extra: demo
Requires-Dist: great-tables>=0.20.0; extra == "demo"
Requires-Dist: matplotlib>=3.7.5; extra == "demo"
Requires-Dist: polars>=1.8.2; extra == "demo"
Dynamic: license-file
